flake8_mypy.py
flake8_mypy_fork-20.5.1.dist-info/LICENSE
flake8_mypy_fork-20.5.1.dist-info/WHEEL
flake8_mypy_fork-20.5.1.dist-info/METADATA
flake8_mypy_fork-20.5.1.dist-info/RECORD
