Metadata-Version: 2.1
Name: flake8-mypy-fork
Version: 20.5.1
Summary: A plugin for flake8 integrating mypy (fork).
License: MIT
Keywords: flake8,mypy,bugs,linter,qa,typing
Author: Łukasz Langa (original)
Author-email: lukasz@langa.pl
Requires-Python: >=3.6,<4.0
Classifier: Development Status :: 3 - Alpha
Classifier: Environment :: Console
Classifier: Framework :: Flake8
Classifier: Intended Audience :: Developers
Classifier: License :: OSI Approved :: MIT License
Classifier: Operating System :: OS Independent
Classifier: Programming Language :: Python
Classifier: Programming Language :: Python :: 3
Classifier: Programming Language :: Python :: 3.5
Classifier: Programming Language :: Python :: 3.6
Classifier: Programming Language :: Python :: 3.7
Classifier: Programming Language :: Python :: 3.8
Classifier: Topic :: Software Development :: Libraries :: Python Modules
Classifier: Topic :: Software Development :: Quality Assurance
Requires-Dist: attrs
Requires-Dist: flake8 (>=3.0.0)
Requires-Dist: mypy
